blast/__init__.py
blast/models/__init__.py
blast/models/_available_models.py
blast/models/degradation_model.py
blast/models/lfp_gr_250AhPrismatic_2019.py
blast/models/lfp_gr_SonyMurata3Ah_2018.py
blast/models/lmo_gr_NissanLeaf66Ah_2ndLife_2020.py
blast/models/nca_gr_Panasonic3Ah_2018.py
blast/models/nca_grsi_SonyMurata2p5Ah_2023.py
blast/models/nmc111_gr_Kokam75Ah_2017.py
blast/models/nmc111_gr_Sanyo2Ah_2014.py
blast/models/nmc622_gr_DENSO50Ah_2021.py
blast/models/nmc811_grSi_LGM50_5Ah_2021.py
blast/models/nmc811_grSi_LGMJ1_4Ah_2020.py
blast/models/nmc_gr_50Ah_B1_2020.py
blast/models/nmc_gr_50Ah_B2_2020.py
blast/models/nmc_gr_75Ah_A_2019.py
blast/models/nmc_lto_10Ah_2020.py
blast/utils/__init__.py
blast/utils/demo.py
blast/utils/functions.py
blast/utils/rainflow.py
blast_lite-1.1.0.dist-info/METADATA
blast_lite-1.1.0.dist-info/WHEEL
blast_lite-1.1.0.dist-info/top_level.txt
blast_lite-1.1.0.dist-info/RECORD
