Metadata-Version: 2.4
Name: BLAST-Lite
Version: 1.1.0
Summary: Tool to model lifetime and degradation for commercial lithium-ion batteries.
Author-email: Paul Gasper <Paul.Gasper@nrel.gov>, Nina Prakash <Nina.Prakash@nrel.gov>, Kandler Smith <Kandler.Smith@nrel.gov>
License: Copyright (c) 2023, Alliance for Sustainable Energy, LLC
Project-URL: Homepage, https://github.com/NREL/BLAST-Lite
Classifier: Programming Language :: Python :: 3
Classifier: License :: OSI Approved :: Apache Software License
Classifier: Operating System :: OS Independent
Requires-Python: <=3.13,>=3.9
Requires-Dist: h5pyd
Requires-Dist: numpy
Requires-Dist: pandas
Requires-Dist: matplotlib
Requires-Dist: scipy
Requires-Dist: nrel-rex
Requires-Dist: geopy
Provides-Extra: dev
Requires-Dist: sphinx; extra == "dev"
Requires-Dist: myst-parser; extra == "dev"
Requires-Dist: sphinx-copybutton; extra == "dev"
Requires-Dist: pydata-sphinx-theme; extra == "dev"
Requires-Dist: ipykernel; extra == "dev"
